pkp.py
pkp-0.6.6.dist-info/LICENSE
pkp-0.6.6.dist-info/METADATA
pkp-0.6.6.dist-info/WHEEL
pkp-0.6.6.dist-info/entry_points.txt
pkp-0.6.6.dist-info/top_level.txt
pkp-0.6.6.dist-info/RECORD
