Metadata-Version: 2.1
Name: pkp
Version: 0.6.6
Summary: Straightforward CLI for KeePass - powered by pykeepass
Author-email: Philipp Schmitt <philipp@schmitt.co>
License: GNU GENERAL PUBLIC LICENSE
Project-URL: documentation, https://github.com/pschmitt/pkp/blob/head/readme.md
Project-URL: homepage, https://github.com/pschmitt/pkp
Project-URL: issues, https://github.com/pschmitt/pkp/issues
Project-URL: repository, https://github.com/pschmitt/pkp
Requires-Python: <4.0,>=3.8
License-File: LICENSE
Requires-Dist: colorama>=0.4.4
Requires-Dist: pykeepass<5.0.0,>=3.2.1
Provides-Extra: dev
Requires-Dist: isort>=5.13.2; extra == "dev"
Requires-Dist: pyinstaller>=4.5; extra == "dev"
Requires-Dist: staticx>=0.14.1; extra == "dev"
